{
  "_generated": "Generated by SweetTooth, do not edit", 
  "description": "Undecorate maximized windows, like Ubuntu's old 'Maximus' package. See readme at extension homepage. Originally at https://bitbucket.org/mathematicalcoffee/maximus-gnome-shell-extension.", 
  "dev-version": "2.4_gnome3.18", 
  "extension-id": "maximus", 
  "gettext-domain": "maximus", 
  "name": "Maximus NG", 
  "settings-schema": "org.gnome.shell.extensions.maximus", 
  "shell-version": [
    "3.18", 
    "3.20", 
    "3.22"
  ], 
  "url": "https://github.com/luispabon/maximus-gnome-shell", 
  "uuid": "maximus@luis.pabon.auronconsulting.co.uk", 
  "version": 9
}